{
    "version": "26.5.0",
    "license": "",
    "extract_dir": "txiki-windows-x86_64",
    "url": "https://github.com/saghul/txiki.js/releases/download/v26.5.0/txiki-windows-x86_64.zip",
    "depends": [
        
    ],
    "homepage": "https://github.com/saghul/txiki.js",
    "hash": "8064a3fbbe772916d200aaffcda12e9dbfa1c7d052a8315b18d8bf4e904b4e79",
    "bin": "",
    "checkver": "github",
    "autoupdate": {
        "url": "https://github.com/saghul/txiki.js/releases/download/v$version/txiki-windows-x86_64.zip"
    }
}
